bitcoinrpc/__init__.py
bitcoinrpc/authproxy.py
python_requests_bitcoinrpc-0.4.0.dist-info/METADATA
python_requests_bitcoinrpc-0.4.0.dist-info/WHEEL
python_requests_bitcoinrpc-0.4.0.dist-info/top_level.txt
python_requests_bitcoinrpc-0.4.0.dist-info/RECORD
