Metadata-Version: 2.1
Name: python-requests-bitcoinrpc
Version: 0.4.0
Summary: Enhanced version python-bitconrpc using requests sessions.
Home-page: https://www.github.com/normoes/python-bitcoinrpc
Author: Norman Moeschter-Schenck
Author-email: <norman.moeschter@gmail.com>
Maintainer: Norman Moeschter-Schenck
Maintainer-email: <norman.moeschter@gmail.com>
License: UNKNOWN
Download-URL: https://github.com/normoes/python-bitcoinrpc/archive/v0.4.0.tar.gz
Platform: UNKNOWN
Classifier: License :: OSI Approved :: MIT License
Classifier: Operating System :: OS Independent
Classifier: Programming Language :: Python :: 3.6
Classifier: Programming Language :: Python :: 3.7
